wsgi_auth_middleware/__about__.py
wsgi_auth_middleware/__init__.py
wsgi_auth_middleware/backends/__init__.py
wsgi_auth_middleware/backends/gssapi.py
wsgi_auth_middleware/backends/pam.py
wsgi_auth_middleware/frontends/__init__.py
wsgi_auth_middleware/frontends/basic.py
wsgi_auth_middleware/frontends/negotiate.py
wsgi_auth_middleware-0.1.2.dist-info/METADATA
wsgi_auth_middleware-0.1.2.dist-info/WHEEL
wsgi_auth_middleware-0.1.2.dist-info/licenses/LICENSE.txt
wsgi_auth_middleware-0.1.2.dist-info/RECORD
