Metadata-Version: 2.3
Name: wsgi-auth-middleware
Version: 0.1.2
Summary: HTTP authentication WSGI middleware
Project-URL: Bugs, https://todo.sr.ht/~svmhdvn/wsgi-auth-middleware
Project-URL: Changelog, https://git.sr.ht/~svmhdvn/wsgi-auth-middleware/refs
Project-URL: Documentation, https://git.sr.ht/~svmhdvn/wsgi-auth-middleware/tree/main/item/README.md
Project-URL: Donate, https://liberapay.com/svmhdvn
Project-URL: Homepage, https://sr.ht/~svmhdvn/wsgi-auth-middleware/
Project-URL: Source, https://git.sr.ht/~svmhdvn/wsgi-auth-middleware/
Author-email: Siva Mahadevan <me@svmhdvn.name>
License-File: LICENSE.txt
Keywords: GSSAPI,HTTP,PAM,WSGI,authentication,kerberos,middleware
Classifier: Development Status :: 4 - Beta
Classifier: License :: OSI Approved :: ISC License (ISCL)
Classifier: Programming Language :: Python
Classifier: Programming Language :: Python :: 3.8
Classifier: Programming Language :: Python :: 3.9
Classifier: Programming Language :: Python :: 3.10
Classifier: Programming Language :: Python :: 3.11
Classifier: Programming Language :: Python :: 3.12
Classifier: Programming Language :: Python :: Implementation :: CPython
Classifier: Programming Language :: Python :: Implementation :: PyPy
Requires-Python: >=3.8
Provides-Extra: gssapi
Requires-Dist: gssapi>=1.8.3; extra == 'gssapi'
Provides-Extra: pam
Requires-Dist: python-pam>=2.0.2; extra == 'pam'
